merkleasy/__init__.py
merkleasy/classes.py
merkleasy/errors.py
merkleasy/interfaces.py
merkleasy/serialization.py
merkleasy/sparse.py
merkleasy/vm.py
merkleasy/xorhashtree.py
merkleasy-0.1.2.dist-info/METADATA
merkleasy-0.1.2.dist-info/WHEEL
merkleasy-0.1.2.dist-info/RECORD
