Metadata-Version: 2.4
Name: merkleasy
Version: 0.1.2
Summary: Easy-to-use Merkle tree library.
Project-URL: Homepage, https://github.com/k98kurz/merkle
Project-URL: Bug Tracker, https://github.com/k98kurz/merkle/issues
Author-email: k98kurz <k98kurz@gmail.com>
Classifier: License :: OSI Approved :: ISC License (ISCL)
Classifier: Operating System :: OS Independent
Classifier: Programming Language :: Python :: 3
Classifier: Topic :: Security :: Cryptography
Requires-Python: >=3.10
